tsp_spanning/__init__.py
tsp_spanning/tsp_wrap.cp310-win32.pyd
tsp_spanning-0.2.dist-info/LICENSE.txt
tsp_spanning-0.2.dist-info/METADATA
tsp_spanning-0.2.dist-info/WHEEL
tsp_spanning-0.2.dist-info/top_level.txt
tsp_spanning-0.2.dist-info/RECORD
