Metadata-Version: 2.1
Name: tsp-spanning
Version: 0.2
Home-page: https://github.com/Czaki/tsp_spanning
Author: Grzegorz Bokota
Author-email: g.bokota@cent.uw.edu.pl
Classifier: Development Status :: 3 - Alpha
Classifier: License :: OSI Approved :: MIT License
Classifier: Operating System :: OS Independent
Classifier: Programming Language :: C++
Classifier: Programming Language :: Python :: Implementation :: CPython
Classifier: Programming Language :: Python :: 3
Classifier: Programming Language :: Python :: 3.6
Classifier: Programming Language :: Python :: 3.7
Classifier: Programming Language :: Python :: 3.8
License-File: LICENSE.txt
Requires-Dist: numpy
Requires-Dist: cython
